setup.cfg
setup.py
dist/lymon-0.2r30dev_r57-py2.5.egg
lymon/__init__.py
lymon.egg-info/PKG-INFO
lymon.egg-info/PKG-INFO~
lymon.egg-info/SOURCES.txt
lymon.egg-info/dependency_links.txt
lymon.egg-info/entry_points.txt
lymon.egg-info/not-zip-safe
lymon.egg-info/paster_plugins.txt
lymon.egg-info/top_level.txt
lymon/core/__init__.py
lymon/core/htmltools.py
lymon/core/metatag.py
lymon/core/serializer.py
lymon/core/webobject.py
lymon/tests/core-test.py
lymon/tests/documents-test.py
lymon/tests/group-test.py
lymon/tw/__init__.py
lymon/tw/site.py
lymon/tw/test.py
lymon/view/__init__.py
lymon/view/csstools.py
lymon/view/selectors.py
lymon/view/test-csstools.py
lymon/view/templates/boder.css