Metadata-Version: 1.0
Name: lymon
Version: 0.2r58dev-r58
Summary: Lymon Web Development Toolkit
Home-page: http://code.google.com/p/lymon/
Author: Laureano Arcanio
Author-email: laureano.arcanio@gmail.com
License: MIT
Platform: UNKNOWN
